LICENSE.txt
MANIFEST.in
setup.py
smsGateway/__init__.py
smsgateway.me_api.egg-info/PKG-INFO
smsgateway.me_api.egg-info/SOURCES.txt
smsgateway.me_api.egg-info/dependency_links.txt
smsgateway.me_api.egg-info/requires.txt
smsgateway.me_api.egg-info/top_level.txt