Metadata-Version: 1.1
Name: smsgateway.me-api
Version: 0.1
Summary: Python package for teh smsgateway.me API
Home-page: https://bitbucket.org/kalua85/python-smsgateway-me
Author: Bastiaan van der Veen
Author-email: nomail@spam.me
License: MIT
Keywords: smsgateway.me,api,sms gateway
Platform: UNKNOWN
Classifier: Development Status :: 3 - Alpha
Classifier: Intended Audience :: Developers
Classifier: Topic :: Software Development :: Build Tools
Classifier: License :: OSI Approved :: MIT License
Classifier: Programming Language :: Python :: 3.4
Classifier: Programming Language :: Python :: 3.5
